blame/__init__.py
blame-0.0.1.dist-info/METADATA
blame-0.0.1.dist-info/WHEEL
blame-0.0.1.dist-info/top_level.txt
blame-0.0.1.dist-info/RECORD
