Metadata-Version: 2.4
Name: blame
Version: 0.0.1
Summary: Development experience insights
Author-email: Alexey Sidorov <ereon.dev@gmail.com>
License: MIT
Requires-Python: >=3.8
